ProjectManagerSdk/__init__.py
ProjectManagerSdk/projectmanagerclient.py
ProjectManagerSdk/tools.py
ProjectManagerSdk/clients/__init__.py
ProjectManagerSdk/clients/apikeyclient.py
ProjectManagerSdk/clients/changesetclient.py
ProjectManagerSdk/clients/dashboardclient.py
ProjectManagerSdk/clients/discussionclient.py
ProjectManagerSdk/clients/fileclient.py
ProjectManagerSdk/clients/holidayclient.py
ProjectManagerSdk/clients/homefileclient.py
ProjectManagerSdk/clients/integrationcategoryclient.py
ProjectManagerSdk/clients/integrationclient.py
ProjectManagerSdk/clients/integrationproviderclient.py
ProjectManagerSdk/clients/licenseclient.py
ProjectManagerSdk/clients/meclient.py
ProjectManagerSdk/clients/notificationclient.py
ProjectManagerSdk/clients/nptclient.py
ProjectManagerSdk/clients/nptdiscussionclient.py
ProjectManagerSdk/clients/nptfilesclient.py
ProjectManagerSdk/clients/nptrecurrencyclient.py
ProjectManagerSdk/clients/nptstatusclient.py
ProjectManagerSdk/clients/npttagclient.py
ProjectManagerSdk/clients/npttodosclient.py
ProjectManagerSdk/clients/projectchargecodeclient.py
ProjectManagerSdk/clients/projectclient.py
ProjectManagerSdk/clients/projectcustomerclient.py
ProjectManagerSdk/clients/projectfieldclient.py
ProjectManagerSdk/clients/projectfileclient.py
ProjectManagerSdk/clients/projectfolderclient.py
ProjectManagerSdk/clients/projectmembersclient.py
ProjectManagerSdk/clients/projectpriorityclient.py
ProjectManagerSdk/clients/projectstatusclient.py
ProjectManagerSdk/clients/projecttemplateclient.py
ProjectManagerSdk/clients/projectversionclient.py
ProjectManagerSdk/clients/resourceclient.py
ProjectManagerSdk/clients/resourceskillclient.py
ProjectManagerSdk/clients/resourceteamclient.py
ProjectManagerSdk/clients/riskclient.py
ProjectManagerSdk/clients/riskfileclient.py
ProjectManagerSdk/clients/tagclient.py
ProjectManagerSdk/clients/taskassigneeclient.py
ProjectManagerSdk/clients/taskclient.py
ProjectManagerSdk/clients/taskfieldclient.py
projectmanagersdk-146.1.229.dist-info/licenses/LICENSE
projectmanagersdk-146.1.229.dist-info/METADATA
projectmanagersdk-146.1.229.dist-info/WHEEL
projectmanagersdk-146.1.229.dist-info/top_level.txt
projectmanagersdk-146.1.229.dist-info/RECORD
