Metadata-Version: 2.4
Name: ProjectManagerSdk
Version: 146.1.229
Summary: Software development kit for the ProjectManager.com API for Python
Author-email: "ProjectManager.com" <support@projectmanager.com>
Project-URL: Homepage, https://github.com/projectmgr/projectmanager-sdk-python
Project-URL: Bug Tracker, https://github.com/projectmgr/projectmanager-sdk-python/issues
Classifier: Programming Language :: Python :: 3
Classifier: License :: OSI Approved :: MIT License
Classifier: Operating System :: OS Independent
Requires-Python: >=3.7
License-File: LICENSE
Requires-Dist: dacite~=1.8.1
Dynamic: license-file
